Metadata-Version: 2.1
Name: fiixclient
Version: 1.1.2
Summary: An easy to use Python wrapper for the Fiix CMMS API
Home-page: https://www.ronaldlangeveld.com
Author: Ronald Langeveld
Author-email: hi@ronaldlangeveld.com
License: MIT
Download-URL: https://github.com/ronaldlangeveld/python-fiix-cmms-client/archive/refs/tags/Latest.tar.gz
Keywords: FIIX,CMMS,API,MAINTENANCE
Platform: UNKNOWN
Classifier: Development Status :: 4 - Beta
Classifier: Intended Audience :: Developers
Classifier: Topic :: Software Development :: Build Tools
Classifier: License :: OSI Approved :: MIT License
Classifier: Programming Language :: Python :: 3.8
Classifier: Programming Language :: Python :: 3.9
